py_autotask/__init__.py
py_autotask/_version.py
py_autotask/async_client.py
py_autotask/auth.py
py_autotask/bulk_manager.py
py_autotask/cache.py
py_autotask/cli.py
py_autotask/cli_enhanced.py
py_autotask/client.py
py_autotask/exceptions.py
py_autotask/pandas_integration.py
py_autotask/types.py
py_autotask/utils.py
py_autotask/caching/__init__.py
py_autotask/caching/cache_config.py
py_autotask/caching/cache_manager.py
py_autotask/entities/__init__.py
py_autotask/entities/accounts.py
py_autotask/entities/action_types.py
py_autotask/entities/additional_invoice_field_values.py
py_autotask/entities/allocation_codes.py
py_autotask/entities/analytics.py
py_autotask/entities/api_usage_metrics.py
py_autotask/entities/appointments.py
py_autotask/entities/article_attachments.py
py_autotask/entities/article_configuration_item_category_associations.py
py_autotask/entities/article_notes.py
py_autotask/entities/article_plain_text_content.py
py_autotask/entities/article_tag_associations.py
py_autotask/entities/article_ticket_associations.py
py_autotask/entities/article_to_article_associations.py
py_autotask/entities/article_to_document_associations.py
py_autotask/entities/attachment_info.py
py_autotask/entities/attachments.py
py_autotask/entities/audit_logs.py
py_autotask/entities/automation_rules.py
py_autotask/entities/backup_configuration.py
py_autotask/entities/base.py
py_autotask/entities/billing_codes.py
py_autotask/entities/billing_item_approval_levels.py
py_autotask/entities/billing_items.py
py_autotask/entities/business_divisions.py
py_autotask/entities/business_rules.py
py_autotask/entities/change_order_charges.py
py_autotask/entities/change_request_links.py
py_autotask/entities/change_requests.py
py_autotask/entities/checklist_libraries.py
py_autotask/entities/checklist_library_checklist_items.py
py_autotask/entities/classification_icons.py
py_autotask/entities/client_portal_users.py
py_autotask/entities/comanaged_associations.py
py_autotask/entities/companies.py
py_autotask-2.0.0.dist-info/METADATA
py_autotask-2.0.0.dist-info/WHEEL
py_autotask-2.0.0.dist-info/entry_points.txt
py_autotask-2.0.0.dist-info/top_level.txt
py_autotask-2.0.0.dist-info/RECORD
