Metadata-Version: 2.4
Name: py-autotask
Version: 2.0.0
Summary: Python library for Autotask PSA REST API integration
Home-page: https://github.com/asachs01/py-autotask
Author: Aaron Sachs
Author-email: Aaron Sachs <dev@sachshaus.net>
Maintainer-email: Aaron Sachs <dev@sachshaus.net>
License: MIT
Project-URL: Homepage, https://github.com/asachs01/py-autotask
Project-URL: Documentation, https://py-autotask.readthedocs.io/
Project-URL: Repository, https://github.com/asachs01/py-autotask.git
Project-URL: Issues, https://github.com/asachs01/py-autotask/issues
Project-URL: Changelog, https://github.com/asachs01/py-autotask/blob/main/CHANGELOG.md
Keywords: autotask,psa,api,rest,integration
Classifier: Development Status :: 4 - Beta
Classifier: Intended Audience :: Developers
Classifier: License :: OSI Approved :: MIT License
Classifier: Operating System :: OS Independent
Classifier: Programming Language :: Python :: 3
Classifier: Programming Language :: Python :: 3.8
Classifier: Programming Language :: Python :: 3.9
Classifier: Programming Language :: Python :: 3.10
Classifier: Programming Language :: Python :: 3.11
Classifier: Programming Language :: Python :: 3.12
Classifier: Topic :: Software Development :: Libraries :: Python Modules
Classifier: Topic :: Office/Business
Classifier: Topic :: Internet :: WWW/HTTP :: Dynamic Content
Requires-Python: >=3.8
Requires-Dist: requests>=2.31.0
Requires-Dist: pydantic>=2.0.0
Requires-Dist: click>=8.0.0
Requires-Dist: python-dotenv>=1.0.0
Requires-Dist: tenacity>=8.0.0
Requires-Dist: httpx>=0.24.0
Requires-Dist: typing-extensions>=4.0.0
Requires-Dist: aiohttp>=3.8.0
Requires-Dist: redis>=4.5.0
Requires-Dist: pandas>=2.0.0
Requires-Dist: openpyxl>=3.1.0
Requires-Dist: pyarrow>=12.0.0
Requires-Dist: tqdm>=4.65.0
Requires-Dist: rich>=10.0.0
Provides-Extra: dev
Requires-Dist: pytest>=6.0; extra == "dev"
Requires-Dist: pytest-cov>=2.10; extra == "dev"
Requires-Dist: pytest-mock>=3.0; extra == "dev"
Requires-Dist: pytest-asyncio>=0.15; extra == "dev"
Requires-Dist: pytest-benchmark>=3.4; extra == "dev"
Requires-Dist: responses>=0.18; extra == "dev"
Requires-Dist: psutil>=5.8.0; extra == "dev"
Requires-Dist: black>=22.0; extra == "dev"
Requires-Dist: isort>=5.10; extra == "dev"
Requires-Dist: flake8>=4.0; extra == "dev"
Requires-Dist: mypy>=0.950; extra == "dev"
Requires-Dist: bandit>=1.7; extra == "dev"
Requires-Dist: safety>=2.0; extra == "dev"
Requires-Dist: pre-commit>=2.15; extra == "dev"
Provides-Extra: docs
Requires-Dist: sphinx>=4.0; extra == "docs"
Requires-Dist: sphinx-rtd-theme>=1.0; extra == "docs"
Requires-Dist: myst-parser>=0.17; extra == "docs"
Requires-Dist: sphinx-autodoc-typehints>=1.12; extra == "docs"
Provides-Extra: test
Requires-Dist: pytest>=6.0; extra == "test"
Requires-Dist: pytest-cov>=2.10; extra == "test"
Requires-Dist: pytest-mock>=3.0; extra == "test"
Requires-Dist: pytest-asyncio>=0.15; extra == "test"
Requires-Dist: pytest-benchmark>=3.4; extra == "test"
Requires-Dist: responses>=0.18; extra == "test"
Requires-Dist: psutil>=5.8.0; extra == "test"
Dynamic: author
Dynamic: home-page
Dynamic: requires-python
